telepythy/__init__.py
telepythy/__main__.py
telepythy/pack.py
telepythy/lib/__init__.py
telepythy/lib/__main__.py
telepythy/lib/event_handlers.py
telepythy/lib/interpreter.py
telepythy/lib/logs.py
telepythy/lib/service.py
telepythy/lib/sockio.py
telepythy/lib/utils.py
telepythy_service-0.5.4.dist-info/METADATA
telepythy_service-0.5.4.dist-info/WHEEL
telepythy_service-0.5.4.dist-info/entry_points.txt
telepythy_service-0.5.4.dist-info/top_level.txt
telepythy_service-0.5.4.dist-info/RECORD
