Metadata-Version: 2.2
Name: telepythy-service
Version: 0.5.4
Home-page: https://github.com/dhagrow/telepythy
Author: Miguel Turner
Author-email: cymrow@gmail.com
Dynamic: author
Dynamic: author-email
Dynamic: description
Dynamic: description-content-type
Dynamic: home-page
